odoo/addons/account_invoice_report_ddt_group/README.rst
odoo/addons/account_invoice_report_ddt_group/__init__.py
odoo/addons/account_invoice_report_ddt_group/__manifest__.py
odoo/addons/account_invoice_report_ddt_group/i18n/account_invoice_report_ddt_group.pot
odoo/addons/account_invoice_report_ddt_group/i18n/am.po
odoo/addons/account_invoice_report_ddt_group/i18n/ar.po
odoo/addons/account_invoice_report_ddt_group/i18n/bg.po
odoo/addons/account_invoice_report_ddt_group/i18n/bs.po
odoo/addons/account_invoice_report_ddt_group/i18n/ca.po
odoo/addons/account_invoice_report_ddt_group/i18n/cs.po
odoo/addons/account_invoice_report_ddt_group/i18n/da.po
odoo/addons/account_invoice_report_ddt_group/i18n/de.po
odoo/addons/account_invoice_report_ddt_group/i18n/el_GR.po
odoo/addons/account_invoice_report_ddt_group/i18n/en_GB.po
odoo/addons/account_invoice_report_ddt_group/i18n/es.po
odoo/addons/account_invoice_report_ddt_group/i18n/es_AR.po
odoo/addons/account_invoice_report_ddt_group/i18n/es_CR.po
odoo/addons/account_invoice_report_ddt_group/i18n/es_EC.po
odoo/addons/account_invoice_report_ddt_group/i18n/es_MX.po
odoo/addons/account_invoice_report_ddt_group/i18n/es_VE.po
odoo/addons/account_invoice_report_ddt_group/i18n/et.po
odoo/addons/account_invoice_report_ddt_group/i18n/fi.po
odoo/addons/account_invoice_report_ddt_group/i18n/fr.po
odoo/addons/account_invoice_report_ddt_group/i18n/fr_CA.po
odoo/addons/account_invoice_report_ddt_group/i18n/fr_CH.po
odoo/addons/account_invoice_report_ddt_group/i18n/gl.po
odoo/addons/account_invoice_report_ddt_group/i18n/hr.po
odoo/addons/account_invoice_report_ddt_group/i18n/hr_HR.po
odoo/addons/account_invoice_report_ddt_group/i18n/hu.po
odoo/addons/account_invoice_report_ddt_group/i18n/id.po
odoo/addons/account_invoice_report_ddt_group/i18n/it.po
odoo/addons/account_invoice_report_ddt_group/i18n/ja.po
odoo/addons/account_invoice_report_ddt_group/i18n/lt.po
odoo/addons/account_invoice_report_ddt_group/i18n/lv.po
odoo12_addon_account_invoice_report_ddt_group-12.0.1.0.5.dist-info/METADATA
odoo12_addon_account_invoice_report_ddt_group-12.0.1.0.5.dist-info/WHEEL
odoo12_addon_account_invoice_report_ddt_group-12.0.1.0.5.dist-info/top_level.txt
odoo12_addon_account_invoice_report_ddt_group-12.0.1.0.5.dist-info/RECORD
