Metadata-Version: 2.1
Name: odoo12-addon-account-invoice-report-ddt-group
Version: 12.0.1.0.5
Summary: Raggruppa le righe fattura per DDT che le ha generate, mostrando eventualmente i lotti/seriali
Home-page: https://github.com/OCA/l10n-italy
Author: Agile Business Group, Apulia Software, Openforce,Odoo Community Association (OCA)
Author-email: support@odoo-community.org
License: AGPL-3
Platform: UNKNOWN
Classifier: Programming Language :: Python
Classifier: Framework :: Odoo
Classifier: License :: OSI Approved :: GNU Affero General Public License v3
Requires-Python: >=3.5
Requires-Dist: odoo12-addon-l10n-it-ddt
Requires-Dist: odoo (<12.1dev,>=12.0a)
